pyelapse.py
pyelapse-0.2.0.dist-info/licenses/LICENSE
pyelapse-0.2.0.dist-info/METADATA
pyelapse-0.2.0.dist-info/WHEEL
pyelapse-0.2.0.dist-info/entry_points.txt
pyelapse-0.2.0.dist-info/top_level.txt
pyelapse-0.2.0.dist-info/RECORD
