Metadata-Version: 2.4
Name: pyelapse
Version: 0.2.0
Summary: A CLI tool to create time-lapse videos from images, with cropping, normalization, and filtering.
Author-email: Silver-Sky <silversky@mail.ch>
Requires-Python: >=3.8
License-File: LICENSE
Requires-Dist: click>=8.0
Requires-Dist: Pillow>=9.0
Requires-Dist: opencv-python>=4.5
Requires-Dist: exifread>=3.0
Dynamic: license-file
